<annotation>
	<folder>image</folder>
	<filename>d_000923_lightup.jpg</filename>
	<path>C:\Users\htc\Desktop\深度学习\image\image\d_000923_lightup.jpg</path>
	<source>
		<database>Unknown</database>
	</source>
	<size>
		<width>688</width>
		<height>544</height>
		<depth>3</depth>
	</size>
	<segmented>0</segmented>
	<object>
		<name>babycarriage</name>
		<pose>Unspecified</pose>
		<truncated>0</truncated>
		<difficult>0</difficult>
		<bndbox>
			<xmin>416</xmin>
			<ymin>77</ymin>
			<xmax>600</xmax>
			<ymax>447</ymax>
		</bndbox>
	</object>
	<object>
		<name>person</name>
		<pose>Unspecified</pose>
		<truncated>0</truncated>
		<difficult>0</difficult>
		<bndbox>
			<xmin>484</xmin>
			<ymin>148</ymin>
			<xmax>608</xmax>
			<ymax>439</ymax>
		</bndbox>
	</object>
	<object>
		<name>person</name>
		<pose>Unspecified</pose>
		<truncated>0</truncated>
		<difficult>0</difficult>
		<bndbox>
			<xmin>352</xmin>
			<ymin>21</ymin>
			<xmax>516</xmax>
			<ymax>211</ymax>
		</bndbox>
	</object>
</annotation>
