<annotation>
	<folder>lq</folder>
	<filename>n_000481_lightup.jpg</filename>
	<path>D:\Users\18234\Desktop\lq\n_000481_lightup.jpg</path>
	<source>
		<database>Unknown</database>
	</source>
	<size>
		<width>640</width>
		<height>480</height>
		<depth>3</depth>
	</size>
	<segmented>0</segmented>
	<object>
		<name>babycarriage</name>
		<pose>Unspecified</pose>
		<truncated>0</truncated>
		<difficult>0</difficult>
		<bndbox>
			<xmin>75</xmin>
			<ymin>51</ymin>
			<xmax>282</xmax>
			<ymax>474</ymax>
		</bndbox>
	</object>
	<object>
		<name>person</name>
		<pose>Unspecified</pose>
		<truncated>0</truncated>
		<difficult>0</difficult>
		<bndbox>
			<xmin>76</xmin>
			<ymin>319</ymin>
			<xmax>196</xmax>
			<ymax>470</ymax>
		</bndbox>
	</object>
</annotation>
